<annotation>
	<folder>clean</folder>
	<filename>WhatsApp Image 2020-10-20 at 7.14.11 PM (14).jpeg</filename>
	<path>train/clean/WhatsApp Image 2020-10-20 at 7.14.11 PM (14).jpeg</path>
	<source>
		<database>clean-dirty-containers-in-montevideo</database>
	</source>
	<size>
		<width>796</width>
		<height>758</height>
		<depth>3</depth>
	</size>
	<segmented>0</segmented>
	<object>
		<name>container</name>
		<pose>Unspecified</pose>
		<truncated>0</truncated>
		<difficult>0</difficult>
		<bndbox>
			<xmin>317</xmin>
			<ymin>261</ymin>
			<xmax>560</xmax>
			<ymax>489</ymax>
		</bndbox>
	</object>
</annotation>
